{
    "schema" : {
            "reactants": {
                "type": "array",
                "as-object": true,
                "description": "Use the 'qty' property when a species appears more than once as a reactant.",
                "children": {
                    "type": "object",
                    "key": "",
                    "children": {
                        "qty": {
                            "type": "integer",
                            "default": 1
                    }
                }
            }
        },
            "products": {
                "type": "array",
                "as-object": true,
                "children": {
                    "type": "object",
                    "key": "",
                    "children": {
                        "yield": {
                            "type": "real",
                            "default": 1.0,
                            "units": "unitless"
                    }
                }
            }
        },
            "scaling factor": {
                "type": "real",
                "default": 1.0,
                "description": "Use the scaling factor to adjust photolysis rate constants from input data. A scaling factor of 1.0 results in no adjustment.",
                "units": "unitless"
        },
            "MUSICA name": {
                "type": "string",
                "description": "Set a MUSICA name for this reaction to identify it in other parts of the model (e.g., input conditions). You may choose any name you like."
        }
    }
}